fimserv/.DS_Store
fimserv/FIMsubset/__init__.py
fimserv/FIMsubset/shpsubset.py
fimserv/FIMsubset/xycoord.py
fimserv/__init__.py
fimserv/datadownload.py
fimserv/plot/__init__.py
fimserv/plot/comparestreamflow.py
fimserv/plot/nwmfid.py
fimserv/plot/src.py
fimserv/plot/usgs.py
fimserv/plot/usgsandfid.py
fimserv/runFIM.py
fimserv/statistics/__init__.py
fimserv/statistics/calculatestatistics.py
fimserv/streamflowdata/__init__.py
fimserv/streamflowdata/forecasteddata.py
fimserv/streamflowdata/nwmretrospective.py
fimserv/vizualizationFIM.py
fimserv-0.1.5.dist-info/LICENSE.txt
fimserv-0.1.5.dist-info/METADATA
fimserv-0.1.5.dist-info/WHEEL
fimserv-0.1.5.dist-info/RECORD
