Metadata-Version: 2.1
Name: fimserv
Version: 0.1.5
Summary: Framework which is developed with the purpose of quickly generating Flood Inundation Maps (FIM) for emergency response and risk assessment. It is developed under Surface Dynamics Modeling Lab (SDML).
Home-page: https://github.com/sdmlua/OperationalOWPFIM
License: GPL-3.0
Author: Supath Dhital
Author-email: sdhital@crimson.ua.edu
Maintainer: Supath Dhital
Maintainer-email: sdhital@crimson.ua.edu
Requires-Python: >=3.10,<3.13
Classifier: License :: OSI Approved :: GNU General Public License v3 (GPLv3)
Classifier: Programming Language :: Python :: 3
Classifier: Programming Language :: Python :: 3.10
Classifier: Programming Language :: Python :: 3.11
Classifier: Programming Language :: Python :: 3.12
Requires-Dist: aiohttp (==3.10.8)
Requires-Dist: awscli (==1.34.23)
Requires-Dist: beautifulsoup4 (>=4.12.3,<5.0.0)
Requires-Dist: botocore (==1.35.23)
Requires-Dist: bottleneck (>=1.3.6,<2.0.0)
Requires-Dist: geemap (>=0.35.1,<0.36.0)
Requires-Dist: ipykernel (>=6.29.5,<7.0.0)
Requires-Dist: localtileserver (>=0.10.5,<0.11.0)
Requires-Dist: matplotlib (>=3.9.2,<4.0.0)
Requires-Dist: netcdf4 (==1.6.5)
Requires-Dist: nodejs-bin (>=18.4.0a4,<19.0.0)
Requires-Dist: numba (>=0.60.0,<0.61.0)
Requires-Dist: numpy (<2.0.0)
Requires-Dist: pyarrow (>=15.0.0,<16.0.0)
Requires-Dist: pytest (>=8.3.3,<9.0.0)
Requires-Dist: python-dotenv (>=1.0.1,<2.0.0)
Requires-Dist: scikit-learn (>=1.5.2,<2.0.0)
Requires-Dist: scipy (>=1.14.1,<2.0.0)
Requires-Dist: tabulate (>=0.9.0,<0.10.0)
Requires-Dist: teehr (==0.4.5)
Requires-Dist: tqdm (>=4.67.0,<5.0.0)
Requires-Dist: utils (>=1.0.2,<2.0.0)
Project-URL: Repository, https://github.com/sdmlua/OperationalOWPFIM
